LICENSE
MANIFEST.in
README.md
setup.py
derpconf/__init__.py
derpconf/config.py
derpconf/version.py
derpconf.egg-info/PKG-INFO
derpconf.egg-info/SOURCES.txt
derpconf.egg-info/dependency_links.txt
derpconf.egg-info/requires.txt
derpconf.egg-info/top_level.txt