Metadata-Version: 2.1
Name: derpconf
Version: 0.8.4
Summary: derpconf abstracts loading configuration files for your app
Home-page: https://github.com/globocom/derpconf
Author: globo.com
Author-email: timehome@corp.globo.com
License: MIT
Keywords: configuration
Classifier: Development Status :: 4 - Beta
Classifier: Intended Audience :: Developers
Classifier: License :: OSI Approved :: MIT License
Classifier: Natural Language :: English
Classifier: Operating System :: MacOS
Classifier: Operating System :: POSIX :: Linux
Classifier: Programming Language :: Python :: 3.9
Classifier: Programming Language :: Python :: 3.10
Classifier: Programming Language :: Python :: 3.11
Classifier: Programming Language :: Python :: 3.12
Provides-Extra: tests
License-File: LICENSE
